jsonc_parser/__init__.py
jsonc_parser/errors.py
jsonc_parser/parser.py
jsonc_parser-1.1.5.dist-info/LICENSE.txt
jsonc_parser-1.1.5.dist-info/METADATA
jsonc_parser-1.1.5.dist-info/WHEEL
jsonc_parser-1.1.5.dist-info/top_level.txt
jsonc_parser-1.1.5.dist-info/RECORD
