Metadata-Version: 2.1
Name: jsonc-parser
Version: 1.1.5
Summary: A lightweight, native tool for parsing .jsonc files
Home-page: https://github.com/NickolaiBeloguzov/jsonc-parser
Author: Nickolai Beloguzov
Author-email: nickolai.beloguzov@gmail.com
License: MIT
Platform: UNKNOWN
Classifier: Programming Language :: Python :: 3
Classifier: Programming Language :: Python :: 3.6
Classifier: Programming Language :: Python :: 3.5
Classifier: Programming Language :: Python :: 3.7
Classifier: Programming Language :: Python :: 3.8
Classifier: Programming Language :: Python :: 3.9
Classifier: License :: OSI Approved :: MIT License
Classifier: Operating System :: OS Independent
Classifier: Development Status :: 5 - Production/Stable
Classifier: Intended Audience :: Developers
Classifier: Natural Language :: English
Requires-Python: >=3.5
